akhq/__init__.py
akhq/akhq.py
akhq.py-0.0.1.dist-info/METADATA
akhq.py-0.0.1.dist-info/WHEEL
akhq.py-0.0.1.dist-info/top_level.txt
akhq.py-0.0.1.dist-info/RECORD
