Metadata-Version: 2.1
Name: akhq.py
Version: 0.0.1
Summary: A Python wrapper for the AKHQ API
Author-email: Theo Nard <theo.nard18@gmail.com>
Keywords: akhq,api,wrapper,python
Classifier: Programming Language :: Python :: 3
Classifier: License :: OSI Approved :: MIT License
Classifier: Operating System :: OS Independent
Requires-Python: >=3.8
Requires-Dist: requests ==2.31.0
